plover_wtype_output/__init__.py
plover_wtype_output-0.0.1.dist-info/LICENSE
plover_wtype_output-0.0.1.dist-info/METADATA
plover_wtype_output-0.0.1.dist-info/WHEEL
plover_wtype_output-0.0.1.dist-info/entry_points.txt
plover_wtype_output-0.0.1.dist-info/top_level.txt
plover_wtype_output-0.0.1.dist-info/zip-safe
plover_wtype_output-0.0.1.dist-info/RECORD
